<?xml version="1.0" encoding="UTF-8"?>

<included>
	<property name="LOG_HOME" value="/home/app/cpstomcat/apache-tomcat-7.0.39" />
	<appender name="CONSOLE" class="ch.qos.logback.core.ConsoleAppender">
		<encoder>
			<pattern>%d %p [%c] - &lt;%m&gt;%n</pattern>
		</encoder>
	</appender>
	<!-- 按照每天生成日志文件 -->
	<appender name="FILE" class="ch.qos.logback.core.rolling.RollingFileAppender">
		<Encoding>UTF-8</Encoding>
		<file>${LOG_HOME}/logs/cps.log</file>
		<rollingPolicy class="ch.qos.logback.core.rolling.TimeBasedRollingPolicy">
			<!--日志文件输出的文件名-->
			<fileNamePattern>${LOG_HOME}/logs/cps-%d{yyyy-MM-dd}.%i.log</fileNamePattern>
			<!-- 可选节点，控制保留的归档文件的最大数量，超出数量就删除旧文件 -->
			<!--<maxHistory>30</maxHistory>-->
	        <TimeBasedFileNamingAndTriggeringPolicy class="ch.qos.logback.core.rolling.SizeAndTimeBasedFNATP">
                    <!--日志文件最大的大小-->
                    <MaxFileSize>100MB</MaxFileSize>
            </TimeBasedFileNamingAndTriggeringPolicy>
		</rollingPolicy>
		<layout class="ch.qos.logback.classic.PatternLayout">
			 <!--格式化输出：%d表示日期，%thread表示线程名，%-5level：级别从左显示5个字符宽度%msg：日志消息，%n是换行符-->
             <Pattern>%d{yyyy-MM-dd HH:mm:ss.SSS} [%thread] %-5level %logger{50} - %msg%n</Pattern>
        </layout>
	</appender>

	<logger name="org.springframework.aop.framework.Cglib2AopProxy"
		level="ERROR" />
	<logger name="org.springframework.web.servlet.mvc.method.annotation.RequestMappingHandlerMapping"
		level="WARN" />

	<logger name="user.access.log" level="INFO" additivity="false">
		<appender-ref ref="FILE" />
	</logger>
	<root level="INFO">
		<appender-ref ref="FILE" />
	</root>
</included>
